MoneyWorld/__init__.py
MoneyWorld/audio/__init__.py
MoneyWorld/video/__init__.py
test/__init__.py
MoneyWorld-2023.9.1.dist-info/LICENSE.txt
MoneyWorld-2023.9.1.dist-info/METADATA
MoneyWorld-2023.9.1.dist-info/WHEEL
MoneyWorld-2023.9.1.dist-info/top_level.txt
MoneyWorld-2023.9.1.dist-info/RECORD
